waivek/__init__.py
waivek/__read_2.py
waivek/ai_truncate.py
waivek/bat.py
waivek/color.py
waivek/common.py
waivek/data.py
waivek/date.py
waivek/db.py
waivek/dbutils.py
waivek/error.py
waivek/error2.py
waivek/frame.py
waivek/get.py
waivek/ic.py
waivek/introspection.py
waivek/json_decode_error.py
waivek/log.py
waivek/markup.py
waivek/null.py
waivek/print_utils.py
waivek/reltools.py
waivek/reqs.py
waivek/table.py
waivek/tdd.py
waivek/template.py
waivek/test.py
waivek/test_debugger.py
waivek/test_import.py
waivek/test_relimport.py
waivek/test_truncate.py
waivek/timer.py
waivek/trace.py
waivek/truncate.py
waivek-0.1.35.dist-info/METADATA
waivek-0.1.35.dist-info/WHEEL
waivek-0.1.35.dist-info/top_level.txt
waivek-0.1.35.dist-info/RECORD
