Metadata-Version: 2.1
Name: waivek
Version: 0.1.35
Summary: UNKNOWN
Home-page: UNKNOWN
License: UNKNOWN
Platform: UNKNOWN
Requires-Dist: aiohttp>=3.8.1
Requires-Dist: columnar==1.3.1
Requires-Dist: executing==0.8.2
Requires-Dist: loguru
Requires-Dist: python-dateutil==2.8.2
Requires-Dist: timeago==1.0.14
Requires-Dist: pysqlite3-binary; platform_system == "Linux"
